{
  "hash": "9214b201",
  "configHash": "24b6c0e6",
  "lockfileHash": "df0f201c",
  "browserHash": "45391389",
  "optimized": {
    "vue": {
      "src": "../../../../../../../node_modules/vue/dist/vue.runtime.esm-bundler.js",
      "file": "vue.js",
      "fileHash": "9c370db8",
      "needsInterop": false
    },
    "vitepress > @vue/devtools-api": {
      "src": "../../../../node_modules/.pnpm/@vue+devtools-api@6.5.1/node_modules/@vue/devtools-api/lib/esm/index.js",
      "file": "vitepress___@vue_devtools-api.js",
      "fileHash": "c63b934c",
      "needsInterop": false
    },
    "vitepress > @vueuse/core": {
      "src": "../../../../node_modules/.pnpm/@vueuse+core@10.7.2_vue@3.4.15/node_modules/@vueuse/core/index.mjs",
      "file": "vitepress___@vueuse_core.js",
      "fileHash": "a3d939f0",
      "needsInterop": false
    },
    "vitepress > @vueuse/integrations/useFocusTrap": {
      "src": "../../../../node_modules/.pnpm/@vueuse+integrations@10.7.2_axios@1.6.7_focus-trap@7.5.4_vue@3.4.15/node_modules/@vueuse/integrations/useFocusTrap.mjs",
      "file": "vitepress___@vueuse_integrations_useFocusTrap.js",
      "fileHash": "8934170f",
      "needsInterop": false
    },
    "vitepress > mark.js/src/vanilla.js": {
      "src": "../../../../node_modules/.pnpm/mark.js@8.11.1/node_modules/mark.js/src/vanilla.js",
      "file": "vitepress___mark__js_src_vanilla__js.js",
      "fileHash": "11cf7f70",
      "needsInterop": false
    },
    "vitepress > minisearch": {
      "src": "../../../../node_modules/.pnpm/minisearch@6.3.0/node_modules/minisearch/dist/es/index.js",
      "file": "vitepress___minisearch.js",
      "fileHash": "8b4a6a30",
      "needsInterop": false
    },
    "axios": {
      "src": "../../../../node_modules/.pnpm/axios@1.6.7/node_modules/axios/index.js",
      "file": "axios.js",
      "fileHash": "19c54ae5",
      "needsInterop": false
    },
    "ant-design-vue": {
      "src": "../../../../node_modules/.pnpm/ant-design-vue@4.1.2_vue@3.4.15/node_modules/ant-design-vue/es/index.js",
      "file": "ant-design-vue.js",
      "fileHash": "14b08828",
      "needsInterop": false
    }
  },
  "chunks": {
    "chunk-4SMZHOOU": {
      "file": "chunk-4SMZHOOU.js"
    },
    "chunk-6UV7G7OM": {
      "file": "chunk-6UV7G7OM.js"
    },
    "chunk-ZS7NZCD4": {
      "file": "chunk-ZS7NZCD4.js"
    }
  }
}